{
    "level_1": {
        "e": [
            "3,2,H,英雄气短", 
            "3,0,V,无名英雄,1", 
            "5,1,V,大气磅礴,3", 
            "1,0,H,有备无患", 
            "1,0,V,有说有笑"
        ], 
        "id": 1361
    }, 
    "level_10": {
        "e": [
            "3,4,H,水中捞月", 
            "3,1,V,斗升之水,2", 
            "5,2,V,大海捞针,0", 
            "1,1,H,争奇斗艳", 
            "1,0,V,谏争如流"
        ], 
        "id": 1370
    }, 
    "level_11": {
        "e": [
            "3,2,H,聊胜于无,3", 
            "3,0,V,百无聊赖,3", 
            "5,1,V,出于无奈", 
            "1,0,H,一呼百应", 
            "1,0,V,一言不合"
        ], 
        "id": 1371
    }, 
    "level_12": {
        "e": [
            "0,4,H,月满则亏", 
            "0,2,V,花前月下,3", 
            "2,1,V,以身作则", 
            "1,1,H,不以为耻,1", 
            "4,0,V,不耻下问"
        ], 
        "id": 1372
    }, 
    "level_13": {
        "e": [
            "0,4,H,攘外安内,1", 
            "0,2,V,熙来攘往", 
            "2,1,V,国泰民安,1", 
            "1,1,H,忧国忧民", 
            "4,0,V,爱民如子"
        ], 
        "id": 1373
    }, 
    "level_14": {
        "e": [
            "1,4,H,百川归海,1", 
            "1,2,V,千疮百孔", 
            "3,1,V,宾至如归,2", 
            "3,1,H,宾客如云", 
            "5,0,V,汗如雨下"
        ], 
        "id": 1374
    }, 
    "level_15": {
        "e": [
            "3,3,H,哀感天地", 
            "3,1,V,喜怒哀乐", 
            "5,2,V,谈天说地,3", 
            "1,1,H,欢天喜地,2", 
            "1,0,V,悲欢离合"
        ], 
        "id": 1375
    }, 
    "level_16": {
        "e": [
            "1,0,H,嬉皮笑脸", 
            "1,0,V,嬉笑怒骂", 
            "3,0,V,笑容可掬,1", 
            "3,2,H,可乘之机,1", 
            "5,1,V,言之有理"
        ], 
        "id": 1376
    }, 
    "level_17": {
        "e": [
            "0,1,H,梅开二度", 
            "0,0,V,望梅止渴,2", 
            "2,1,V,二龙戏珠,2", 
            "2,4,H,珠联璧合", 
            "5,2,V,通力合作"
        ], 
        "id": 1377
    }, 
    "level_18": {
        "e": [
            "3,3,H,喜怒无常,2", 
            "3,0,V,转悲为喜,1", 
            "5,1,V,束手无策", 
            "1,0,H,顺风转舵", 
            "1,0,V,顺时而动"
        ], 
        "id": 1378
    }, 
    "level_19": {
        "e": [
            "0,1,H,暮鼓晨钟", 
            "0,0,V,迟暮之年,2", 
            "2,1,V,晨光熹微", 
            "1,4,H,防微杜渐,3", 
            "4,2,V,循序渐进"
        ], 
        "id": 1379
    }, 
    "level_2": {
        "e": [
            "3,3,H,怜香惜玉,3", 
            "3,0,V,顾影自怜", 
            "5,1,V,依依惜别", 
            "1,0,H,无所顾忌,3", 
            "1,0,V,无机可乘"
        ], 
        "id": 1362
    }, 
    "level_20": {
        "e": [
            "0,3,H,志在千里,2", 
            "0,2,V,赍志而殁,1", 
            "2,1,V,一日千里", 
            "2,1,H,一字一泪", 
            "5,0,V,热泪盈眶"
        ], 
        "id": 1380
    }, 
    "level_21": {
        "e": [
            "3,2,H,同病相怜", 
            "3,1,V,大同小异,3", 
            "5,0,V,萍水相逢", 
            "1,4,H,奇光异彩,1", 
            "1,1,V,不足为奇"
        ], 
        "id": 1381
    }, 
    "level_22": {
        "e": [
            "0,3,H,星星点点,1", 
            "0,1,V,月明星稀", 
            "2,3,V,点石成金,2", 
            "0,1,H,月白风清", 
            "1,5,H,自成一家"
        ], 
        "id": 1382
    }, 
    "level_23": {
        "e": [
            "0,3,H,身首异处,2", 
            "0,2,V,安身立命", 
            "2,0,V,标新立异,0", 
            "1,0,H,孤标傲世", 
            "0,5,H,命中注定"
        ], 
        "id": 1383
    }, 
    "level_24": {
        "e": [
            "1,3,H,卑鄙无耻", 
            "1,0,V,男尊女卑,2", 
            "3,2,V,万无一失", 
            "0,0,H,红男绿女,0", 
            "0,5,H,得不偿失"
        ], 
        "id": 1384
    }, 
    "level_25": {
        "e": [
            "1,1,H,小肚鸡肠,2", 
            "1,1,V,小心翼翼", 
            "3,0,V,偷鸡摸狗", 
            "3,3,H,狗皮膏药,1", 
            "5,2,V,焚膏继晷"
        ], 
        "id": 1385
    }, 
    "level_26": {
        "e": [
            "3,3,H,见缝插针", 
            "3,0,V,视而不见,3", 
            "5,1,V,两肋插刀", 
            "1,0,H,混淆视听,2", 
            "1,0,V,混水摸鱼"
        ], 
        "id": 1386
    }, 
    "level_27": {
        "e": [
            "0,2,H,泽被后世,3", 
            "0,1,V,竭泽而渔", 
            "2,0,V,前赴后继", 
            "2,0,H,前功尽弃,2", 
            "5,0,V,弃暗投明"
        ], 
        "id": 1387
    }, 
    "level_28": {
        "e": [
            "0,3,H,声泪俱下,0", 
            "0,3,V,声名狼藉,0", 
            "2,1,V,与日俱增", 
            "2,1,H,与虎谋皮", 
            "5,1,V,皮里阳秋"
        ], 
        "id": 1388
    }, 
    "level_29": {
        "e": [
            "1,2,H,丝丝入扣,0", 
            "1,2,V,丝竹管弦", 
            "3,0,V,酣然入梦", 
            "3,0,H,酣畅淋漓,1", 
            "1,5,H,弦外之音"
        ], 
        "id": 1389
    }, 
    "level_3": {
        "e": [
            "0,3,H,火树银花", 
            "0,2,V,星火燎原,1", 
            "2,1,V,铁画银钩,1", 
            "2,1,H,铁树开花", 
            "5,0,V,风花雪月"
        ], 
        "id": 1363
    }, 
    "level_30": {
        "e": [
            "1,0,H,逍遥自在", 
            "1,0,V,逍遥自得", 
            "3,0,V,自由自在,1", 
            "3,2,H,自崖而反,3", 
            "5,1,V,周而复始"
        ], 
        "id": 1390
    }, 
    "level_31": {
        "e": [
            "3,3,H,非分之想,1", 
            "3,0,V,大是大非", 
            "5,1,V,后起之秀", 
            "1,0,H,破口大骂,3", 
            "1,0,V,破旧立新"
        ], 
        "id": 1391
    }, 
    "level_32": {
        "e": [
            "3,4,H,至圣先师,2", 
            "3,1,V,关怀备至", 
            "5,2,V,未卜先知,2", 
            "1,1,H,事不关己", 
            "1,0,V,一事无成"
        ], 
        "id": 1392
    }, 
    "level_33": {
        "e": [
            "1,4,H,绞尽脑汁,2", 
            "1,1,V,心如刀绞,1", 
            "3,1,V,缩头缩脑", 
            "3,1,H,缩衣节食", 
            "5,0,V,晚节不保"
        ], 
        "id": 1393
    }, 
    "level_34": {
        "e": [
            "2,1,H,堆积如山", 
            "3,1,V,积劳成疾,2", 
            "5,0,V,江山如故,1", 
            "0,3,H,坐享其成", 
            "0,0,V,平起平坐"
        ], 
        "id": 1394
    }, 
    "level_35": {
        "e": [
            "1,3,H,来龙去脉,3", 
            "1,2,V,常来常往", 
            "3,0,V,扬长而去,3", 
            "1,0,H,分道扬镳", 
            "0,5,H,数往知来"
        ], 
        "id": 1395
    }, 
    "level_36": {
        "e": [
            "3,3,H,息息相关", 
            "3,0,V,生生不息", 
            "5,1,V,朝夕相处,0", 
            "1,0,H,无中生有,1", 
            "1,0,V,无地自容"
        ], 
        "id": 1396
    }, 
    "level_37": {
        "e": [
            "1,4,H,话中带刺,3", 
            "1,2,V,不在话下,2", 
            "3,2,V,一衣带水", 
            "3,2,H,一席之地", 
            "5,0,V,胯下之辱"
        ], 
        "id": 1397
    }, 
    "level_38": {
        "e": [
            "2,3,H,妙手偶得,0", 
            "2,3,V,妙不可言", 
            "4,1,V,并威偶势", 
            "2,1,H,兼容并包,1", 
            "0,5,H,寥寥可数"
        ], 
        "id": 1398
    }, 
    "level_39": {
        "e": [
            "2,3,H,悲从中来", 
            "2,0,V,乐极生悲,0", 
            "4,2,V,个中滋味,2", 
            "0,0,H,幸灾乐祸", 
            "1,5,H,别有风味"
        ], 
        "id": 1399
    }, 
    "level_4": {
        "e": [
            "1,3,H,忘恩负义,2", 
            "1,0,V,过目不忘", 
            "3,2,V,不负众望,3", 
            "0,0,H,功过是非", 
            "0,5,H,大失所望"
        ], 
        "id": 1364
    }, 
    "level_40": {
        "e": [
            "3,3,H,天之骄子", 
            "3,1,V,包打天下,2", 
            "5,2,V,戒骄戒躁,0", 
            "1,1,H,色胆包天", 
            "1,0,V,好色之徒"
        ], 
        "id": 1400
    }, 
    "level_5": {
        "e": [
            "1,1,H,削足适履,0", 
            "1,0,V,笔削褒贬,1", 
            "3,1,V,适得其反", 
            "3,3,H,其乐融融", 
            "5,2,V,孔融让梨"
        ], 
        "id": 1365
    }, 
    "level_6": {
        "e": [
            "0,3,H,以和为贵", 
            "0,2,V,聊以自慰", 
            "2,1,V,不足为据,2", 
            "2,1,H,不期而遇,0", 
            "5,0,V,随遇而安"
        ], 
        "id": 1366
    }, 
    "level_7": {
        "e": [
            "1,1,H,平铺直叙", 
            "1,0,V,心平气和", 
            "3,1,V,直上直下,2", 
            "3,3,H,直抒己见,2", 
            "5,2,V,推己及人"
        ], 
        "id": 1367
    }, 
    "level_8": {
        "e": [
            "3,4,H,语焉不详,0", 
            "3,1,V,好言好语,0", 
            "5,2,V,敬谢不敏", 
            "1,1,H,乐善好施", 
            "1,0,V,鼓乐喧天"
        ], 
        "id": 1368
    }, 
    "level_9": {
        "e": [
            "2,2,H,呲牙咧嘴", 
            "3,1,V,以牙还牙,2", 
            "5,1,V,七嘴八舌", 
            "0,4,H,佶屈聱牙,1", 
            "1,3,V,不屈不挠"
        ], 
        "id": 1369
    }
}